<?xml version='1.0' encoding='us-ascii'?>
<annotation>
	<folder>voc2012</folder>
	<filename>212.jpg</filename>
	<path>C:/Users/86151/Desktop/game/geetest/pic/212.jpg</path>
	<source>
		<database>Unknown</database>
	</source>
	<size>
		<width>344</width>
		<height>384</height>
		<depth>3</depth>
	</size>
	<segmented>0</segmented>
		<object>
		<name>D0D3</name>
		<pose>Unspecified</pose>
		<truncated>0</truncated>
		<difficult>0</difficult>
		<bndbox>
			<xmin>98</xmin>
			<ymin>36</ymin>
			<xmax>161</xmax>
			<ymax>100</ymax>
		</bndbox>
	</object>
	<object>
		<name>C8CA</name>
		<pose>Unspecified</pose>
		<truncated>0</truncated>
		<difficult>0</difficult>
		<bndbox>
			<xmin>177</xmin>
			<ymin>127</ymin>
			<xmax>240</xmax>
			<ymax>191</ymax>
		</bndbox>
	</object>
	<object>
		<name>ECC0</name>
		<pose>Unspecified</pose>
		<truncated>0</truncated>
		<difficult>0</difficult>
		<bndbox>
			<xmin>192</xmin>
			<ymin>227</ymin>
			<xmax>255</xmax>
			<ymax>291</ymax>
		</bndbox>
	</object>
	<object>
		<name>C8E2</name>
		<pose>Unspecified</pose>
		<truncated>0</truncated>
		<difficult>0</difficult>
		<bndbox>
			<xmin>215</xmin>
			<ymin>50</ymin>
			<xmax>278</xmax>
			<ymax>114</ymax>
		</bndbox>
	</object>
</annotation>