<?xml version='1.0' encoding='us-ascii'?>
<annotation>
	<folder>voc2012</folder>
	<filename>000791.jpg</filename>
	<path>C:/Users/86151/Desktop/game/geetest/pic/000791.jpg</path>
	<source>
		<database>Unknown</database>
	</source>
	<size>
		<width>344</width>
		<height>384</height>
		<depth>3</depth>
	</size>
	<segmented>0</segmented>
		<object>
		<name>DCBD</name>
		<pose>Unspecified</pose>
		<truncated>0</truncated>
		<difficult>0</difficult>
		<bndbox>
			<xmin>103</xmin>
			<ymin>149</ymin>
			<xmax>167</xmax>
			<ymax>215</ymax>
		</bndbox>
	</object>
	<object>
		<name>C8D8</name>
		<pose>Unspecified</pose>
		<truncated>0</truncated>
		<difficult>0</difficult>
		<bndbox>
			<xmin>211</xmin>
			<ymin>225</ymin>
			<xmax>275</xmax>
			<ymax>291</ymax>
		</bndbox>
	</object>
	<object>
		<name>B2CD</name>
		<pose>Unspecified</pose>
		<truncated>0</truncated>
		<difficult>0</difficult>
		<bndbox>
			<xmin>77</xmin>
			<ymin>239</ymin>
			<xmax>141</xmax>
			<ymax>305</ymax>
		</bndbox>
	</object>
	<object>
		<name>CCFC</name>
		<pose>Unspecified</pose>
		<truncated>0</truncated>
		<difficult>0</difficult>
		<bndbox>
			<xmin>198</xmin>
			<ymin>131</ymin>
			<xmax>262</xmax>
			<ymax>197</ymax>
		</bndbox>
	</object>
</annotation>